leila/__init__.py
leila/calidad_datos.py
leila/datos_gov.py
leila/reporte.py
leila/templates/template.html
leila-0.2.dist-info/LICENSE
leila-0.2.dist-info/METADATA
leila-0.2.dist-info/WHEEL
leila-0.2.dist-info/top_level.txt
leila-0.2.dist-info/RECORD
