Metadata-Version: 2.1
Name: leila
Version: 0.2
Summary: Librería para medir la calidad de los datos en conjuntos de datos estructurados
Home-page: https://github.com/ucd-dnp/leila
Author: Departamento Nacional de Planeación - DNP
Author-email: ucd@dnp.gov.co
Maintainer: Unidad de Científicos de Datos - UCD
Maintainer-email: ucd@dnp.gov.co
License: MIT
Project-URL: Documentación, https://ucd-dnp.github.io/leila/
Project-URL: Seguimiento de fallas, https://github.com/ucd-dnp/leila/issues
Keywords: Python,Calidad de datos,UCD,DNP
Platform: UNKNOWN
Classifier: License :: OSI Approved :: MIT License
Classifier: Operating System :: Microsoft :: Windows
Classifier: Operating System :: POSIX :: Linux
Classifier: Programming Language :: Python :: 3.6
Classifier: Programming Language :: Python :: 3.7
Classifier: Programming Language :: Python :: 3.8
Classifier: Programming Language :: Python :: 3.9
Requires-Python: >=3.6.2
License-File: LICENSE
Requires-Dist: jinja2 (>=3.0.3)
Requires-Dist: openpyxl (>=3.0.9)
Requires-Dist: pandas (>=1.1.5)
Requires-Dist: phik (>=0.12.0)
Requires-Dist: requests (>=2.26.0)
Requires-Dist: scipy (>=1.5.4)
Requires-Dist: unidecode (>=1.3.2)
Requires-Dist: xlrd (>=2.0.1)
